.VERSION
AUTHORS.rst
CONTRIBUTING.rst
HISTORY.rst
LICENSE
MANIFEST.in
Pipfile
Pipfile.lock
README.rst
USAGE.rst
dev-requirements.txt
requirements.txt
setup.cfg
setup.py
docs/Makefile
docs/authors.rst
docs/conf.py
docs/contributing.rst
docs/history.rst
docs/index.rst
docs/installation.rst
docs/readme.rst
docs/usage.rst
locationsharinglib/.VERSION
locationsharinglib/AUTHORS.rst
locationsharinglib/CONTRIBUTING.rst
locationsharinglib/HISTORY.rst
locationsharinglib/LICENSE
locationsharinglib/Pipfile
locationsharinglib/Pipfile.lock
locationsharinglib/README.rst
locationsharinglib/USAGE.rst
locationsharinglib/__init__.py
locationsharinglib/_version.py
locationsharinglib/dev-requirements.txt
locationsharinglib/locationsharinglib.py
locationsharinglib/locationsharinglibexceptions.py
locationsharinglib/requirements.txt
locationsharinglib.egg-info/PKG-INFO
locationsharinglib.egg-info/SOURCES.txt
locationsharinglib.egg-info/dependency_links.txt
locationsharinglib.egg-info/not-zip-safe
locationsharinglib.egg-info/requires.txt
locationsharinglib.egg-info/top_level.txt
tests/test_locationsharinglib.py