Metadata-Version: 2.1
Name: locationsharinglib
Version: 5.0.3
Summary: A library to retrieve coordinates from an google account that has been shared locations of other accounts.
Home-page: https://github.com/costastf/locationsharinglib
Author: Costas Tyfoxylos
Author-email: costas.tyf@gmail.com
License: MIT
Keywords: locationsharinglib google maps location sharing
Classifier: Development Status :: 4 - Beta
Classifier: Intended Audience :: Developers
Classifier: License :: OSI Approved :: MIT License
Classifier: Natural Language :: English
Classifier: Programming Language :: Python :: 3.9
License-File: LICENSE
License-File: AUTHORS.rst
Requires-Dist: coloredlogs>=15.0.1; python_version >= "2.7" and python_version not in "3.0, 3.1, 3.2, 3.3, 3.4"
Requires-Dist: requests>=2.31.0; python_version >= "3.7"
Requires-Dist: cachetools>=5.3.2; python_version >= "3.7"
Requires-Dist: pytz>=2023.3.post1
Requires-Dist: dataclasses~=0.6; python_version == "3.6"
